// class version 47.0 (47)
// access flags 0x21
public class jdk3/ArtificialStructures {

  // compiled from: ArtificialStructures.java
  // debug info: source-debug

  ATTRIBUTE Comment : unknown

  // access flags 0x1001
  public synthetic I f
  ATTRIBUTE Comment : unknown

  // access flags 0x1001
  public synthetic <init>(Ljava/lang/String;)V
  ATTRIBUTE Comment : unknown
    ALOAD 0
    INVOKESPECIAL java/lang/Object.<init> ()V
    NOP
    RETURN
  ATTRIBUTE CodeComment : unknown
    MAXSTACK = 1
    MAXLOCALS = 2

  // access flags 0x0
  <init>(Z)V
    ILOAD 1
    ALOAD 0
    SWAP
    IFEQ L0
    LDC "1"
    GOTO L1
   L0
    LINENUMBER 1 L0
    LINENUMBER 3 L0
   FRAME FULL [U I] [U]
    LDC "0"
   L1
    LINENUMBER 5 L1
    LINENUMBER 7 L1
    LINENUMBER 11 L1
    LINENUMBER 13 L1
    LINENUMBER 17 L1
   FRAME FULL [U I] [U java/lang/String]
    INVOKESPECIAL jdk3/ArtificialStructures.<init> (Ljava/lang/String;)V
    RETURN
    MAXSTACK = 2
    MAXLOCALS = 2

  // access flags 0x8
  static dup_x2(IJ)V
    LLOAD 1
    ILOAD 0
    DUP_X2
    I2L
    LADD
    INVOKESTATIC jdk3/ArtificialStructures.dup_x2 (IJ)V
    RETURN
    MAXSTACK = 5
    MAXLOCALS = 3

  // access flags 0x8
  static dup2_x2(IIII)V
    ILOAD 3
    ILOAD 2
    ILOAD 1
    ILOAD 0
    DUP2_X2
    IADD
    IADD
    INVOKESTATIC jdk3/ArtificialStructures.dup2_x2 (IIII)V
    RETURN
    MAXSTACK = 6
    MAXLOCALS = 4

  // access flags 0x8
  static dup2_x2(IIJ)V
    LLOAD 2
    ILOAD 1
    ILOAD 0
    DUP2_X2
    IADD
    I2L
    LADD
    INVOKESTATIC jdk3/ArtificialStructures.dup2_x2 (IIJ)V
    RETURN
    MAXSTACK = 6
    MAXLOCALS = 4

  // access flags 0x8
  static dup2_x2(JD)V
    DLOAD 2
    LLOAD 0
    DUP2_X2
    L2D
    DADD
    INVOKESTATIC jdk3/ArtificialStructures.dup2_x2 (JD)V
    RETURN
    MAXSTACK = 6
    MAXLOCALS = 4
}
